clayful/__init__.py
clayful/exception/__init__.py
clayful/models/__init__.py
clayful/models/brand.py
clayful/models/cart.py
clayful/models/catalog.py
clayful/models/collection.py
clayful/models/country.py
clayful/models/coupon.py
clayful/models/currency.py
clayful/models/customer.py
clayful/models/discount.py
clayful/models/downloadable.py
clayful/models/group.py
clayful/models/image.py
clayful/models/impression.py
clayful/models/order.py
clayful/models/order_tag.py
clayful/models/payment_method.py
clayful/models/product.py
clayful/models/review.py
clayful/models/review_comment.py
clayful/models/shipping_method.py
clayful/models/store.py
clayful/models/subscription.py
clayful/models/subscription_plan.py
clayful/models/tax_category.py
clayful/models/tracker.py
clayful/models/wish_list.py
clayful/requester/__init__.py
clayful/response/__init__.py
tests/__init__.py
tests/test_clayful.py
tests/test_exception.py
tests/test_requester.py
clayful-1.0.0.dist-info/LICENSE
clayful-1.0.0.dist-info/METADATA
clayful-1.0.0.dist-info/WHEEL
clayful-1.0.0.dist-info/top_level.txt
clayful-1.0.0.dist-info/RECORD
