Metadata-Version: 2.1
Name: clayful
Version: 1.0.0
Summary: Python SDK for Clayful API
Home-page: https://github.com/Clayful/clayful-python
Author: Daeik Kim
Author-email: daeik.kim@clayful.io
License: MIT
Keywords: eCommerce clayful
Platform: UNKNOWN
Requires-Dist: requests (<3,>2.1)
Provides-Extra: test
Requires-Dist: httpretty (>0.8); extra == 'test'
